Workbook

Sheet Order Register
A1: Order ID | B1: Order Date | C1: Customer | D1: Contact Person | E1: Product | F1: Quantity | G1: Unit Price | H1: Total Value | I1: Payment Status | J1: Order Status | K1: Priority | L1: Expected Delivery | M1: Follow-Up Date | N1: Assigned To | O1: Notes | P1: Order Health
A2: ORD-1001 | B2: 2026-09-01 | C2: BluePeak Consulting | D2: Lerato Mokoena | E2: Laptop Stand | F2: 12 | G2: 450 | H2: =IF(OR(F2="",G2=""),"",F2*G2) | I2: Partially Paid | J2: Processing | K2: Normal | L2: 2026-09-05 | M2: 2026-09-03 | N2: Sipho | O2: Customer requested delivery confirmation | P2: =IF(OR(I2="Overdue",J2="On Hold",K2="Urgent"),"Action Required",IF(J2="Delivered","Complete","On Track"))
A3: ORD-1002 | B3: 2026-09-01 | C3: Greenline Logistics | D3: Thabo Ndlovu | E3: Wireless Keyboard | F3: 25 | G3: 680 | H3: =IF(OR(F3="",G3=""),"",F3*G3) | I3: Paid | J3: Ready for Dispatch | K3: High | L3: 2026-09-04 | M3: 2026-09-02 | N3: Amanda | O3: Stock confirmed | P3: =IF(OR(I3="Overdue",J3="On Hold",K3="Urgent"),"Action Required",IF(J3="Delivered","Complete","On Track"))
A4: ORD-1003 | B4: 2026-09-02 | C4: Horizon Legal Services | D4: Naledi Dlamini | E4: 24-inch Monitor | F4: 8 | G4: 3200 | H4: =IF(OR(F4="",G4=""),"",F4*G4) | I4: Pending | J4: Awaiting Payment | K4: High | L4: 2026-09-07 | M4: 2026-09-04 | N4: Sipho | O4: Invoice sent to customer | P4: =IF(OR(I4="Overdue",J4="On Hold",K4="Urgent"),"Action Required",IF(J4="Delivered","Complete","On Track"))
A5: ORD-1004 | B5: 2026-09-02 | C5: MetroBuild Projects | D5: Jason Williams | E5: Office Chair | F5: 15 | G5: 1850 | H5: =IF(OR(F5="",G5=""),"",F5*G5) | I5: Paid | J5: Processing | K5: Normal | L5: 2026-09-08 | M5: 2026-09-05 | N5: Amanda | O5: Assembly required | P5: =IF(OR(I5="Overdue",J5="On Hold",K5="Urgent"),"Action Required",IF(J5="Delivered","Complete","On Track"))
A6: ORD-1005 | B6: 2026-09-03 | C6: Coastal Media Group | D6: Zanele Jacobs | E6: USB-C Docking Station | F6: 6 | G6: 2100 | H6: =IF(OR(F6="",G6=""),"",F6*G6) | I6: Pending | J6: On Hold | K6: Urgent | L6: 2026-09-06 | M6: 2026-09-04 | N6: Sipho | O6: Customer requested updated quotation | P6: =IF(OR(I6="Overdue",J6="On Hold",K6="Urgent"),"Action Required",IF(J6="Delivered","Complete","On Track"))
A7: ORD-1006 | B7: 2026-09-03 | C7: PrimeCare Supplies | D7: Musa Khumalo | E7: Wireless Mouse | F7: 30 | G7: 390 | H7: =IF(OR(F7="",G7=""),"",F7*G7) | I7: Paid | J7: Dispatched | K7: Normal | L7: 2026-09-06 | M7: 2026-09-05 | N7: Amanda | O7: Courier tracking shared | P7: =IF(OR(I7="Overdue",J7="On Hold",K7="Urgent"),"Action Required",IF(J7="Delivered","Complete","On Track"))
A8: ORD-1007 | B8: 2026-09-04 | C8: Summit Engineering | D8: Pieter Botha | E8: Laptop | F8: 5 | G8: 12500 | H8: =IF(OR(F8="",G8=""),"",F8*G8) | I8: Paid | J8: Processing | K8: High | L8: 2026-09-10 | M8: 2026-09-06 | N8: Sipho | O8: Awaiting final configuration | P8: =IF(OR(I8="Overdue",J8="On Hold",K8="Urgent"),"Action Required",IF(J8="Delivered","Complete","On Track"))
A9: ORD-1008 | B9: 2026-09-04 | C9: Atlas Property Group | D9: Nomsa Cele | E9: Printer | F9: 3 | G9: 6800 | H9: =IF(OR(F9="",G9=""),"",F9*G9) | I9: Pending | J9: Awaiting Payment | K9: Normal | L9: 2026-09-09 | M9: 2026-09-06 | N9: Amanda | O9: Payment reminder required | P9: =IF(OR(I9="Overdue",J9="On Hold",K9="Urgent"),"Action Required",IF(J9="Delivered","Complete","On Track"))
A10: ORD-1009 | B10: 2026-09-05 | C10: Eastway Accounting | D10: Kim Adams | E10: External Hard Drive | F10: 10 | G10: 1450 | H10: =IF(OR(F10="",G10=""),"",F10*G10) | I10: Paid | J10: Delivered | K10: Low | L10: 2026-09-08 | M10: 2026-09-07 | N10: Sipho | O10: Customer confirmed receipt | P10: =IF(OR(I10="Overdue",J10="On Hold",K10="Urgent"),"Action Required",IF(J10="Delivered","Complete","On Track"))
A11: ORD-1010 | B11: 2026-09-05 | C11: NovaTech Solutions | D11: Bongani Maseko | E11: 24-inch Monitor | F11: 12 | G11: 3200 | H11: =IF(OR(F11="",G11=""),"",F11*G11) | I11: Overdue | J11: On Hold | K11: Urgent | L11: 2026-09-09 | M11: 2026-09-07 | N11: Amanda | O11: Payment overdue; order paused | P11: =IF(OR(I11="Overdue",J11="On Hold",K11="Urgent"),"Action Required",IF(J11="Delivered","Complete","On Track"))
A12: ORD-1011 | B12: 2026-09-06 | C12: Westbridge Architects | D12: Claire Daniels | E12: Office Desk | F12: 7 | G12: 4200 | H12: =IF(OR(F12="",G12=""),"",F12*G12) | I12: Paid | J12: Processing | K12: Normal | L12: 2026-09-12 | M12: 2026-09-08 | N12: Sipho | O12: Delivery slot being arranged | P12: =IF(OR(I12="Overdue",J12="On Hold",K12="Urgent"),"Action Required",IF(J12="Delivered","Complete","On Track"))
A13: ORD-1012 | B13: 2026-09-06 | C13: PeakPoint Marketing | D13: Andile Ncube | E13: Webcam | F13: 10 | G13: 950 | H13: =IF(OR(F13="",G13=""),"",F13*G13) | I13: Paid | J13: Ready for Dispatch | K13: High | L13: 2026-09-10 | M13: 2026-09-08 | N13: Amanda | O13: Dispatch scheduled | P13: =IF(OR(I13="Overdue",J13="On Hold",K13="Urgent"),"Action Required",IF(J13="Delivered","Complete","On Track"))

Sheet Order Summary
A1: NEXA ORDER MANAGEMENT DASHBOARD
A2: Sales Operations & Order Management Overview
A4: Total Orders | C4: Total Order Value | E4: Orders Requiring Action | G4: Current Pipeline Value
A5: =COUNTA('Order Register'!A:A)-1 | C5: =SUM('Order Register'!H:H) | E5: =COUNTIF('Order Register'!P:P,"Action Required") | G5: =SUMIFS('Order Register'!H:H,'Order Register'!J:J,"<>Delivered",'Order Register'!J:J,"<>Cancelled")
A7: Delivered Orders | B7: =COUNTIF('Order Register'!J:J,"Delivered") | C7: Orders Awaiting Payment | D7: =COUNTIF('Order Register'!J:J,"Awaiting Payment") | E7: Data Source | F7: Order Register table
A10: ORDER STATUS | D10: STATUS | E10: COUNT
D11: New | E11: =COUNTIF('Order Register'!J:J,D11)
D12: Processing | E12: =COUNTIF('Order Register'!J:J,D12)
D13: Awaiting Payment | E13: =COUNTIF('Order Register'!J:J,D13)
D14: Ready for Dispatch | E14: =COUNTIF('Order Register'!J:J,D14)
D15: Dispatched | E15: =COUNTIF('Order Register'!J:J,D15)
D16: Delivered | E16: =COUNTIF('Order Register'!J:J,D16)
D17: On Hold | E17: =COUNTIF('Order Register'!J:J,D17)
D18: Cancelled | E18: =COUNTIF('Order Register'!J:J,D18)
